relay_transformer/__init__.py
relay_transformer/autopadder.py
relay_transformer/autoregressive_wrapper.py
relay_transformer/relay_transformer.py
relay_transformer/reversible.py
relay_transformer-0.0.5.dist-info/LICENSE
relay_transformer-0.0.5.dist-info/METADATA
relay_transformer-0.0.5.dist-info/WHEEL
relay_transformer-0.0.5.dist-info/top_level.txt
relay_transformer-0.0.5.dist-info/RECORD
