Metadata-Version: 2.1
Name: relay-transformer
Version: 0.0.5
Summary: Relay Transformer, a long-range transformer
Home-page: https://github.com/lucidrains/relay-transformer
Author: Phil Wang
Author-email: lucidrains@gmail.com
License: MIT
Keywords: transformers,attention,artificial intelligence
Platform: UNKNOWN
Classifier: Development Status :: 4 - Beta
Classifier: Intended Audience :: Developers
Classifier: Topic :: Scientific/Engineering :: Artificial Intelligence
Classifier: License :: OSI Approved :: MIT License
Classifier: Programming Language :: Python :: 3.6
Requires-Dist: torch
Requires-Dist: local-attention
